Clipper_Python-0.1.1.dist-info/DESCRIPTION.rst
Clipper_Python-0.1.1.dist-info/METADATA
Clipper_Python-0.1.1.dist-info/RECORD
Clipper_Python-0.1.1.dist-info/WHEEL
Clipper_Python-0.1.1.dist-info/metadata.json
Clipper_Python-0.1.1.dist-info/top_level.txt
clipper_python/__init__.py
clipper_python/_foo.so
clipper_python/det_npp.py
clipper_python/test_clipper.py
clipper_python/test_cpatterson.py
clipper_python/test_minimol.py
clipper_python/include/fftw.h
clipper_python/include/rfftw.h
clipper_python/include/ccp4/ccp4_array.h
clipper_python/include/ccp4/ccp4_errno.h
clipper_python/include/ccp4/ccp4_file_err.h
clipper_python/include/ccp4/ccp4_fortran.h
clipper_python/include/ccp4/ccp4_general.h
clipper_python/include/ccp4/ccp4_parser.h
clipper_python/include/ccp4/ccp4_program.h
clipper_python/include/ccp4/ccp4_spg.h
clipper_python/include/ccp4/ccp4_sysdep.h
clipper_python/include/ccp4/ccp4_types.h
clipper_python/include/ccp4/ccp4_unitcell.h
clipper_python/include/ccp4/ccp4_utils.h
clipper_python/include/ccp4/ccp4_vars.h
clipper_python/include/ccp4/cmap_data.h
clipper_python/include/ccp4/cmap_errno.h
clipper_python/include/ccp4/cmap_header.h
clipper_python/include/ccp4/cmap_labels.h
clipper_python/include/ccp4/cmap_skew.h
clipper_python/include/ccp4/cmap_stats.h
clipper_python/include/ccp4/cmaplib.h
clipper_python/include/ccp4/cmaplib_f.h
clipper_python/include/ccp4/cmtzlib.h
clipper_python/include/ccp4/csymlib.h
clipper_python/include/ccp4/cvecmat.h
clipper_python/include/ccp4/library_file.h
clipper_python/include/ccp4/mtzdata.h
clipper_python/include/ccp4/overview.h
clipper_python/include/ccp4/pack_c.h
clipper_python/include/ccp4/w32mvs.h
clipper_python/include/clipper/clipper-ccp4.h
clipper_python/include/clipper/clipper-cctbx.h
clipper_python/include/clipper/clipper-cif.h
clipper_python/include/clipper/clipper-cns.h
clipper_python/include/clipper/clipper-contrib.h
clipper_python/include/clipper/clipper-minimol.h
clipper_python/include/clipper/clipper-mmdb.h
clipper_python/include/clipper/clipper-phs.h
clipper_python/include/clipper/clipper.h
clipper_python/include/clipper/minimal-clipper-hkl.h
clipper_python/include/clipper/minimal-clipper-map.h
