Metadata-Version: 2.0
Name: Clipper-Python
Version: 0.1.1
Summary: Clipper libraries for experimental structural biology data
Home-page: https://github.com/clipper-python
Author: Stuart McNicholas, Tristan Croll, Tom Burnley, Colin Palmer, Soon Wen Hoh, Huw T. Jenkins, Eleanor Dodson, Kevin Cowtan, Jon Agirre
Author-email: clipper-python@york.ac.uk
License: LGPLv3+
Keywords: protein biomolecule biology crystal x-ray electron microscopy cryo-EM
Platform: UNKNOWN
Classifier: Development Status :: 3 - Alpha
Classifier: Intended Audience :: Developers
Classifier: Topic :: Software Development :: Libraries
Classifier: License :: OSI Approved :: GNU Lesser General Public License v3 or later (LGPLv3+)
Classifier: Programming Language :: Python :: 2.7
Classifier: Programming Language :: Python :: 3.4
Classifier: Programming Language :: Python :: 3.5
Classifier: Programming Language :: Python :: 3.6
Requires-Dist: numpy (>=1.13.1)
